{"attorna_general":{"layout":"full","boxed-layout-top-margin":"0px","body-margin":"0px","background-type":"color","background-image":"","background-image-opacity":"100","background-pattern":"pattern-1","enable-boxed-border":"disable","item-padding":"20px","container-width":"1320px","container-padding":"20px","sidebar-title-divider":"disable","sidebar-width":"20","both-sidebar-width":"15","enable-top-bar":"disable","enable-top-bar-on-mobile":"disable","top-bar-width":"boxed","top-bar-width-pixel":"1140px","top-bar-full-side-padding":"15px","top-bar-menu-position":"none","top-bar-left-text":"[gdlr_core_icon icon=\"fa fa-phone\" size=\"15px\" color=\"#b1976b\" margin-left=\"\" margin-right=\"10px\" ]+1-2345-2345-54<div style=\"margin-left: 12px; margin-right: 14px; display: inline;\">&#183;<\/div>[gdlr_core_icon icon=\"fa fa-envelope-open-o\" size=\"14px\" color=\"#b1976b\" margin-left=\"\" margin-right=\"10px\" ]<a href=\"mailto:admin@logiscotheme.co\">Contact@Attornasite.co<\/a> <div style=\"margin-left: 10px; margin-right: 13px; display: inline;\">&#183;<\/div>[gdlr_core_icon icon=\"icon_clock_alt\" size=\"15px\" color=\"#b1976b\" margin-left=\"\" margin-right=\"10px\" ]Mon - Fri 09:00-17:00","top-bar-right-text":"","top-bar-top-padding":"16px","top-bar-bottom-padding":"16px","top-bar-text-size":"15px","top-bar-bottom-border":"0px","enable-top-bar-social":"enable","top-bar-social-delicious":"","top-bar-social-email":"","top-bar-social-deviantart":"","top-bar-social-digg":"","top-bar-social-facebook":"#","top-bar-social-flickr":"","top-bar-social-google-plus":"","top-bar-social-lastfm":"","top-bar-social-linkedin":"#","top-bar-social-pinterest":"#","top-bar-social-rss":"","top-bar-social-skype":"","top-bar-social-stumbleupon":"","top-bar-social-tumblr":"","top-bar-social-twitter":"#","top-bar-social-vimeo":"","top-bar-social-youtube":"","top-bar-social-instagram":"#","top-bar-social-snapchat":"","header-style":"plain","header-plain-style":"menu-right","header-plain-bottom-border":"0px","header-bar-navigation-align":"center","header-background-style":"solid","top-bar-background-opacity":"50","header-background-opacity":"50","navigation-background-opacity":"50","header-boxed-style":"menu-right","boxed-top-bar-background-opacity":"0","boxed-top-bar-background-extend":"0px","boxed-header-top-margin":"0px","header-side-style":"top-left","header-side-align":"left","header-side-toggle-style":"left","header-side-toggle-menu-type":"overlay","header-side-toggle-display-logo":"enable","header-width":"boxed","header-width-pixel":"1140px","header-full-side-padding":"15px","boxed-header-frame-radius":"3px","boxed-header-content-padding":"30px","navigation-text-top-margin":"0px","navigation-text-top-margin-boxed":"0px","navigation-text-side-spacing":"18px","navigation-left-offset":"0","navigation-slide-bar":"enable","navigation-slide-bar-top-margin":"-51px","side-header-width-pixel":"340px","side-header-side-padding":"70px","navigation-text-top-spacing":"16px","logo-right-text":"","logo-right-text-top-padding":"30px","logo":"","logo-top-padding":"51px","logo-bottom-padding":"51px","logo-left-padding":"","max-logo-width":"200px","mobile-logo":"","max-tablet-logo-width":"150px","max-mobile-logo-width":"120px","mobile-logo-position":"logo-left","main-navigation-top-padding":"56px","main-navigation-bottom-padding":"57px","main-navigation-item-right-padding":"0px","main-navigation-right-padding":"","enable-main-navigation-submenu-indicator":"disable","navigation-right-top-margin":"","enable-main-navigation-search":"enable","enable-main-navigation-cart":"enable","enable-main-navigation-right-button":"disable","main-navigation-right-button-style":"default","main-navigation-right-button-text":"Buy Now","main-navigation-right-button-link":"Free consultant ","main-navigation-right-button-link-target":"_self","right-menu-type":"right","right-menu-style":"hamburger-with-border","enable-main-navigation-sticky":"enable","enable-logo-on-main-navigation-sticky":"enable","fixed-navigation-bar-logo":"","fixed-navigation-max-logo-width":"150px","fixed-navigation-logo-top-padding":"25","fixed-navigation-logo-bottom-padding":"20","fixed-navigation-top-padding":"27","fixed-navigation-bottom-padding":"30","fixed-navigation-anchor-offset":"75px","enable-mobile-navigation-sticky":"enable","default-title-style":"custom","default-title-align":"center","default-title-top-padding":"136px","default-title-bottom-padding":"130px","default-page-caption-top-margin":"17px","default-title-font-transform":"none","default-title-font-size":"51px","default-title-font-weight":"700","default-title-letter-spacing":"0px","default-caption-font-transform":"uppercase","default-caption-font-size":"14px","default-caption-font-weight":"700","default-caption-letter-spacing":"3px","page-title-top-bottom-gradient":"none","page-title-top-gradient-size":"413px","page-title-bottom-gradient-size":"413px","default-title-background-overlay-opacity":"0","default-title-background":"","default-portfolio-title-background":"","default-personnel-title-background":"","default-search-title-background":"","default-archive-title-background":"","default-404-background":"","default-404-background-opacity":"27","default-blog-title-style":"custom","default-blog-title-top-padding":"150px","default-blog-title-bottom-padding":"80px","default-blog-feature-image":"none","default-blog-title-background-image":"","default-blog-top-bottom-gradient":"bottom","single-blog-title-top-gradient-size":"325px","single-blog-title-bottom-gradient-size":"346px","default-blog-title-background-overlay-opacity":"2","blog-style":"style-1","blockquote-style":"style-1","blog-sidebar":"right","blog-sidebar-left":"gdlr-core-sidebar-preset","blog-sidebar-right":"gdlr-core-sidebar-preset","blog-max-content-width":"900px","blog-thumbnail-size":"full","blog-date-feature":"enable","blog-date-feature-year":"disable","meta-option":["author","category","tag","comment"],"blog-author":"enable","blog-navigation":"enable","pagination-style":"round","pagination-align":"right","enable-related-post":"enable","related-post-blog-style":"blog-column","related-post-blog-column-style":"style-3","related-post-column-size":"20","related-post-meta-option":["date","author"],"related-post-thumbnail-size":"Portfolio Thumbnail","related-post-num-fetch":"3","related-post-excerpt-number":"0","blog-social-share":"enable","blog-social-share-count":"disable","blog-social-facebook":"enable","blog-social-linkedin":"disable","blog-social-google-plus":"enable","blog-social-pinterest":"enable","blog-social-stumbleupon":"disable","blog-social-twitter":"enable","blog-social-email":"disable","archive-blog-sidebar":"right","archive-blog-sidebar-left":"gdlr-core-sidebar-preset","archive-blog-sidebar-right":"gdlr-core-sidebar-preset","archive-blog-style":"blog-full","archive-blog-full-style":"style-1","archive-blog-side-thumbnail-style":"style-1","archive-blog-column-style":"style-1","archive-blog-image-style":"style-1","archive-blog-full-alignment":"left","archive-thumbnail-size":"full","archive-show-thumbnail":"enable","archive-column-size":"20","archive-excerpt":"specify-number","archive-excerpt-number":"55","archive-date-feature":"enable","archive-meta-option":["date","author","category"],"archive-show-read-more":"enable","archive-blog-title-font-size":"","archive-blog-title-font-weight":"","archive-blog-title-letter-spacing":"","archive-blog-title-text-transform":"none","woocommerce-archive-sidebar":"right","woocommerce-archive-sidebar-left":"gdlr-core-sidebar-preset","woocommerce-archive-sidebar-right":"gdlr-core-sidebar-preset","woocommerce-archive-product-style":"grid-2","woocommerce-archive-column-size":"20","woocommerce-archive-thumbnail":"full","woocommerce-related-product-column-size":"20","woocommerce-related-product-num-fetch":"3","woocommerce-related-product-thumbnail":"full","portfolio-slug":"portfolio","portfolio-category-slug":"portfolio_category","portfolio-tag-slug":"portfolio_tag","enable-single-portfolio-navigation":"disable","enable-single-portfolio-navigation-in-same-tag":"enable","portfolio-icon-hover-link":"icon_link_alt","portfolio-icon-hover-video":"icon_film","portfolio-icon-hover-image":"arrow_expand","portfolio-icon-hover-size":"22px","enable-related-portfolio":"disable","related-portfolio-style":"grid","related-portfolio-column-size":"15","related-portfolio-num-fetch":"4","related-portfolio-thumbnail-size":"medium","related-portfolio-num-excerpt":"20","archive-portfolio-sidebar":"none","archive-portfolio-sidebar-left":"gdlr-core-sidebar-preset","archive-portfolio-sidebar-right":"gdlr-core-sidebar-preset","archive-portfolio-style":"medium","archive-portfolio-thumbnail-size":"full","archive-portfolio-grid-text-align":"left","archive-portfolio-grid-style":"normal","archive-enable-portfolio-tag":"enable","archive-portfolio-medium-size":"small","archive-portfolio-medium-style":"switch","archive-portfolio-hover":"icon","archive-portfolio-column-size":"20","archive-portfolio-excerpt":"specify-number","archive-portfolio-excerpt-number":"55","personnel-slug":"personnel","personnel-category-slug":"personnel_category","fixed-footer":"disable","enable-footer":"enable","footer-background":"","enable-footer-column-divider":"disable","footer-top-padding":"75px","footer-bottom-padding":"60px","footer-style":"footer-3","enable-copyright":"enable","copyright-style":"left-right","copyright-top-padding":"38px","copyright-bottom-padding":"38px","copyright-text":"","copyright-left":"","copyright-right":"","enable-back-to-top":"disable","top-bar-right-button-icon-class":"","top-bar-right-button-text":"Get A Quote","top-bar-right-button-link":"","top-bar-right-button-link-target":"_self","top-bar-shadow-size":"24px","top-bar-shadow-color":"#000","header-shadow-size":"24px","header-shadow-color":"#000","enable-logo":"enable"},"attorna_typography":{"heading-font":"Poppins","navigation-font":"Poppins","content-font":"Poppins","info-font":"Poppins","blog-info-font":"Poppins","quote-font":"Montserrat","testimonial-font":"Merriweather","additional-font":"Georgia, serif","additional-font2":"Georgia, serif","h1-font-size":"47px","h2-font-size":"41px","h3-font-size":"30px","h4-font-size":"24px","h5-font-size":"21px","h6-font-size":"18px","header-font-weight":"","content-font-size":"16px","content-font-weight":"","content-line-height":"1.7","mobile-h1-font-size":"","mobile-h2-font-size":"","mobile-h3-font-size":"","mobile-h4-font-size":"","mobile-h5-font-size":"","mobile-h6-font-size":"","mobile-content-font-size":"","navigation-font-size":"15px","navigation-font-weight":"500","navigation-font-letter-spacing":"","navigation-text-transform":"none","navigation-right-button-font-size":"6px","navigation-right-button-font-weight":"","navigation-right-button-font-letter-spacing":"","navigation-right-button-text-transform":"uppercase","sidebar-title-font-size":"16px","sidebar-title-font-weight":"700","sidebar-title-font-letter-spacing":"0px","sidebar-title-text-transform":"none","footer-title-font-size":"18px","footer-title-font-weight":"700","footer-title-font-letter-spacing":"0px","footer-title-text-transform":"none","footer-font-size":"16px","footer-content-font-weight":"","footer-content-text-transform":"none","copyright-font-size":"16px","copyright-font-weight":"400","copyright-font-letter-spacing":"0px","copyright-text-transform":"none","font-upload":""},"attorna_color":{"header-background-color":"#ffffff","top-cart-background-color":"#232323","top-cart-checkout-color":"#b1976b","secondary-menu-icon-color":"#3f3f3f","secondary-menu-border-color":"#3f3f3f","main-menu-text-hover-color":"#262626","sub-menu-background-color":"#191919","navigation-bar-right-icon-color":"#3f3f3f","main-menu-text-color":"#5d5d5d","woocommerce-theme-color":"#b1976b","woocommerce-price-color":"#707070","woocommerce-button-background-hover-color":"#b1976b","add-to-cart-background-color":"#b1976b","widget-price-filter-range-color":"#b1976b","widget-price-filter-handle-color":"#af853b","top-bar-social-hover-color":"#897351","navigation-slide-bar-color":"#b1976b","woocommerce-cart-icon-number-background":"#b1976b","woocommerce-cart-icon-number-color":"#ffffff","top-bar-background-color":"#ffffff","top-bar-bottom-border-color":"#ffffff","top-bar-text-color":"#8e8e8e","top-bar-link-color":"#8e8e8e","top-bar-link-hover-color":"#897351","top-bar-social-color":"#b1976b","header-plain-bottom-border-color":"#e8e8e8","logo-background-color":"#ffffff","search-overlay-background-color":"#000000","top-cart-text-color":"#b5b5b5","top-cart-view-cart-color":"#323232","breadcrumbs-text-color":"#c0c0c0","breadcrumbs-text-active-color":"#777777","navigation-bar-background-color":"#f4f4f4","navigation-bar-top-border-color":"#e8e8e8","sub-menu-text-color":"#bebebe","sub-menu-text-hover-color":"#ffffff","sub-menu-text-hover-background-color":"#1c1c1c","sub-mega-menu-title-color":"#ffffff","sub-mega-menu-divider-color":"#424242","side-menu-text-color":"#979797","side-menu-text-hover-color":"#ffffff","side-menu-background-color":"#1f1f1f","side-menu-border-color":"#626262","overlay-menu-background-color":"#000000","overlay-menu-border-color":"#424242","overlay-menu-text-color":"#ffffff","overlay-menu-text-hover-color":"#a8a8a8","anchor-bullet-background-color":"#777777","anchor-bullet-background-active-color":"#ffffff","navigation-right-text-color":"#ffffff","navigation-right-button-text-color":"#333333","navigation-right-button-text-hover-color":"#555555","navigation-right-button-background-color":"","navigation-right-button-background-hover-color":"","navigation-right-button-border-color":"#333333","navigation-right-button-border-hover-color":"#555555","page-preload-background-color":"#ffffff","body-background-color":"#ffffff","container-background-color":"#ffffff","page-title-color":"#ffffff","page-caption-color":"#ffffff","page-title-background-overlay-color":"#000000","body-content-color":"#555555","heading-color":"#161616","link-color":"#3d3d3d","link-hover-color":"#606060","divider-color":"#e6e6e6","input-box-background-color":"#ffffff","input-box-border-color":"#e0e0e0","input-box-text-color":"#4e4e4e","input-box-placeholder-color":"#5e5e5e","404-content-background-color":"#23618e","404-head-color":"#ffffff","404-title-color":"#ffffff","404-caption-color":"#c3e7ff","404-input-background-color":"#000000","404-input-text-color":"#ffffff","404-back-to-home-color":"#ffffff","sidebar-title-color":"#383838","sidebar-link-color":"#282828","sidebar-link-hover-color":"#b1976b","recent-post-widget-info-icon-color":"#9c9c9c","recent-post-widget-info-link-color":"#a0a0a0","post-slider-widget-title-color":"#ffffff","post-slider-widget-info-color":"#9c9c9c","search-box-text-color":"#727272","search-box-border-color":"#f3f3f3","search-box-icon-color":"#c7c7c7","twitter-widget-icon-color":"#303030","twitter-widget-date-color":"#b5b5b5","custom-menu-widget-list-style-link":"#4c4c4c","custom-menu-widget-list-style-link-hover":"#b1976b","custom-menu-widget-list-style-border":"#dddddd","footer-background-color":"#1d1d1d","footer-title-color":"#ffffff","footer-content-color":"#ababab","footer-link-color":"#b1a17d","footer-link-hover-color":"#ffffff","footer-divider-color":"#444444","copyright-background-color":"#111111","copyright-text-color":"#a3a3a3","copyright-link-color":"#838383","copyright-link-hover-color":"#838383","back-to-top-background-color":"#dbdbdb","back-to-top-text-color":"#313131","single-blog-title-color":"#ffffff","single-blog-info-color":"#ffffff","single-blog-date-day-color":"#ffffff","single-blog-date-month-color":"#b1b1b1","single-blog-divider-color":"#ffffff","single-blog-title-background-overlay-color":"#000000","single-blog-author-title-color":"#464646","single-blog-author-caption-color":"#b1b1b1","single-blog-style-2-tags-color":"#b1976b","single-blog-navigation-color":"#b1976b","single-blog-navigation2-left-overlay":"#b1976b","single-blog-navigation2-overlay":"#b1976b","single-blog-2-related-post-background":"#f5f5f5","single-blog-magazine-tags-text":"#8d8d8d","single-blog-magazine-tags-background":"#f2f2f2","single-blog-magazine-author-background":"#f7f7f7","single-blog-comment-title-color":"#464646","single-blog-comment-background-color":"#ffffff","single-blog-comment-reply-color":"#bcbcbc","single-blog-comment-time-color":"#b1b1b1","blog-title-color":"#191919","blog-title-hover-color":"#b1976b","blog-sticky-banner-color":"#444444","blog-sticky-banner-background":"#f3f3f3","blog-info-color":"#959595","blog-date-day-color":"#353535","blog-date-month-color":"#8a8a8a","blog-frame-background-color":"#ffffff","blog-modern-hover-background-color":"#000","blog-thumbnail-category-background":"#b1976b","blog-modern-text-color":"#ffffff","blog-aside-background-color":"#b1976b","blog-aside-text-color":"#ffffff","pagination-background-color":"#f0f0f0","pagination-text-color":"#828282","pagination-background-hover-color":"#b1976b","pagination-text-hover-color":"#ffffff","pagination-plain-color":"#b4b4b4","pagination-plain-hover-color":"#424242","single-portfolio-nav-color":"#828282","portfolio-frame-background-color":"#ffffff","portfolio-title-color":"#191919","portfolio-title-hover-color":"","portfolio-info-head-color":"#343434","portfolio-info-color":"#b1b1b1","portfolio-grid2-tag-background":"#b1976b","portfolio-badge-text-color":"#0a0a0a","portfolio-badge-background-color":"#b1976b","portfolio-thumbnail-title-color":"#ffffff","portfolio-thumbnail-info-color":"#cecece","portfolio-text-filter-color":"#aaaaaa","portfolio-text-filter-active-color":"#161616","portfolio-button-filter-text-color":"#838383","portfolio-button-filter-background-color":"#f1f1f1","portfolio-button-filter-text-active-color":"#191919","portfolio-button-filter-background-active-color":"#b1976b","price-table-background-color":"#ffffff","price-table-head-color":"#3e3e3e","price-table-head-top-gradient-color":"#3e3e3e","price-table-icon-color":"#ffffff","price-table-title-color":"#b1976b","price-table-caption-color":"#ffffff","price-table-price-background-color":"#f6f6f6","price-table-price-color":"#323232","price-table-price-suffix-color":"#191919","price-table-price-button-color":"#ffffff","price-table-button-background-color":"#383838","price-table-button-background-top-gradient-color":"#383838","price-table-list-border-color":"#e5e5e5","price-table-active-head-color":"#b1976b","price-table-active-head-top-gradient-color":"#b1976b","price-table-active-icon-color":"#ffffff","price-table-active-title-color":"#ffffff","price-table-active-caption-color":"#fff3f2","price-table-active-price-background-color":"#f6f6f6","price-table-active-price-color":"#323232","price-table-active-price-suffix-color":"#191919","price-table-active-price-button-color":"#ffffff","price-table-active-button-background-color":"#b1976b","price-table-active-button-background-top-gradient-color":"#b1976b","accordion-normal-icon-color":"#4c4c4c","accordion-normal-title-head-color":"#4c4c4c","accordion-normal-title-color":"#4c4c4c","accordion-normal-icon-background-color":"#f3f3f3","accordion-icon-color":"#989898","accordion-title-head-color":"#191919","accordion-title-color":"#989898","accordion-title-background-color":"#f3f3f3","accordion-icon-active-color":"#ffffff","accordion-title-active-color":"#ffffff","accordion-title-background-active-color":"#b1976b","audio-background-color":"#e7e7e7","audio-text-color":"#202020","audio-content-background-color":"#afafaf","audio-content-progress-color":"#b1976b","audio-volume-background-color":"#afafaf","audio-volume-progress-color":"#646464","alert-box-item-background-color":"#ef5e68","alert-box-item-border-color":"#cd515a","alert-box-item-content-color":"#ffffff","alert-box-item-title-color":"#ffffff","blockquote-text-color":"#777777","blockquote-background-color":"#f5f5f5","blockquote-border-color":"#e2e2e2","blockquote-item-icon-color":"#b1976b","blockquote-item-content-color":"#1c1c1c","button-text-color":"#ffffff","button-text-hover-color":"#ffffff","button-background-color":"#b1976b","button-background-hover-color":"#2F2F2F","button-border-color":"#383838","button-border-hover-color":"#000000","button-gradient-background-color":"#b1976b","button-top-gradient-background-color":"#a8803a","call-to-action-title-color":"#2c2c2c","call-to-action-caption-color":"#535353","counter-item-top-text-color":"#828282","counter-item-top-icon-color":"#393939","counter-item-number-color":"#393939","counter-item-divider-color":"#393939","counter-item-bottom-text-color":"#7d7d7d","column-service-icon-color":"#9d9d9d","column-service-icon-background":"#f3f3f3","column-service-title-color":"#383838","column-service-caption-color":"#747474","dropdown-tab-head-background":"#b1976b","dropdown-tab-head-text":"#252525","flipbox-background-color":"#b1976b","flipbox-border-color":"#af8f57","flipbox-icon-color":"#ffffff","flipbox-title-color":"#ffffff","flipbox-caption-color":"#ffffff","flipbox-content-color":"#ffffff","gallery-overlay-title":"#ffffff","gallery-overlay-caption":"#cecece","image-overlay-background-color":"#000000","image-overlay-icon-color":"#ffffff","image-overlay-icon-background":"#ffffff","image-item-border-color":"#000000","item-title-color":"#343434","item-title-caption-color":"#747474","item-title-link-color":"#747474","icon-list-item-icon-color":"#222222","icon-list-item-icon-background-color":"#f3f3f3","opening-hour-day-color":"#a5a5a5","opening-hour-open-color":"#262626","opening-hour-close-color":"#c8c8c8","opening-hour-icon-color":"#8a8989","opening-hour-divider-color":"#a6a6a6","personnel-grid-title-color":"#383838","personnel-grid-position-color":"#9d9d9d","personnel-grid-divider-color":"#b1976b","personnel-grid-frame-color":"#ffffff","personnel-modern-title-color":"#ffffff","personnel-modern-position-color":"#ffffff","promo-box-item-title-color":"#383838","promo-box-content-border-color":"#e8e7e7","post-slider-title-color":"#ffffff","post-slider-info-color":"#c5c5c5","roadmap-title-color":"#d8c0b1","roadmap-title-active-color":"#ffffff","roadmap-caption-color":"#ddc5b5","roadmap-number-text":"#c5c5c5","roadmap-number-background":"#b1976b","roadmap-number-active-text":"#b1976b","roadmap-number-active-background":"#ffffff","roadmap-number-divider":"#ffffff","roadmap-content-title":"#ffffff","roadmap-content-caption":"#ddc5b5","roadmap-content-color":"#ddc5b5","skill-bar-title-color":"#505050","skill-bar-icon-color":"#616161","skill-bar-background-color":"#f3f3f3","skill-bar-progress-color":"#b1976b","slider-outer-navigation-color":"#b1976b","slider-outer-navigation-background-color":"#ffffff","slider-control-navigation-color":"#8a8a8a","slider-control-navigation-background-color":"#dfdfdf","social-share-icon-color":"#202020","social-share-divider-color":"#e5e5e5","social-share-text-color":"#202020","stunning-text-title-color":"#747474","stunning-text-caption-color":"#383838","tab-title-color":"#8d8d8d","tab-title-background-color":"#f7f7f7","tab-title-border-color":"#ebebeb","tab-title-hover-bar-color":"#b1976b","tab-title-active-color":"#464646","tab-title-active-background-color":"#ffffff","table-head-background-color":"#b1976b","table-head-text-color":"#ffffff","table-odd-background-color":"#f9f9f9","table-odd-text-color":"#949494","table-even-background":"#f3f3f3","table-even-text":"#949494","testimonial-title-color":"#232323","testimonial-content-color":"#707070","testimonial-author-color":"#3b3b3b","testimonial-rating-color":"#ffa127","testimonial-position-color":"#3b3b3b","testimonial-quote-color":"#282828","title-item-title-color":"#161616","title-item-caption-color":"#747474","woocommerce-price-linethrough-color":"#949494","woocommerce-button-text-color":"#ffffff","woocommerce-button-text-hover-color":"#ffffff","woocommerce-input-background-color":"#f3f3f3","product-item-title-color":"#191919","product-item-title-hover-color":"#434343","view-detail-text-color":"#ffffff","view-detail-background-color":"#000000","add-to-cart-text-color":"#ffffff","widget-price-filter-bar-background-color":"#e6e6e6","skin":[{"name":"White Text","title":"#ffffff","title-hover":"","caption":"#a1a1a1","content":"#ffffff","icon":"#ffffff","link":"#b1976b","link-hover":"#b1976b","divider":"","border":"","element-background":"#111111","element-content":"","button-text":"","button-text-hover":"","button-background":"","button-background-hover":"","button-border-color":"","button-border-hover-color":""},{"name":"Dark Personnel","title":"#ffffff","title-hover":"","caption":"#5db0b8","content":"","icon":"#ffffff","link":"#ffffff","link-hover":"","divider":"#5db0b8","border":"","element-background":"","element-content":"","button-text":"","button-text-hover":"","button-background":"","button-background-hover":"","button-border-color":"","button-border-hover-color":""},{"name":"Our Philosophy","title":"#ffffff","title-hover":"","caption":"#b0b0b0","content":"#b0b0b0","icon":"","link":"","link-hover":"","divider":"","border":"","element-background":"","element-content":"","button-text":"","button-text-hover":"","button-background":"","button-background-hover":"","button-border-color":"","button-border-hover-color":""},{"name":"client consultation","title":"#202020","title-hover":"","caption":"#b1976b","content":"#b1976b","icon":"","link":"","link-hover":"","divider":"","border":"","element-background":"","element-content":"","button-text":"","button-text-hover":"","button-background":"","button-background-hover":"","button-border-color":"","button-border-hover-color":""},{"name":"frequently asked","title":"#ffffff","title-hover":"#b1976b","caption":"#b8b8b8","content":"","icon":"#ffffff","link":"","link-hover":"","divider":"#474747","border":"#474747","element-background":"","element-content":"#474747","button-text":"","button-text-hover":"","button-background":"","button-background-hover":"","button-border-color":"","button-border-hover-color":""},{"name":"white client","title":"#ffffff","title-hover":"","caption":"#b1976b","content":"#b1976b","icon":"","link":"","link-hover":"","divider":"","border":"","element-background":"","element-content":"","button-text":"","button-text-hover":"","button-background":"","button-background-hover":"","button-border-color":"","button-border-hover-color":""},{"name":"Accordion","title":"#ffffff","title-hover":"#b1976b","caption":"","content":"#b8b8b8","icon":"","link":"","link-hover":"","divider":"","border":"","element-background":"","element-content":"","button-text":"","button-text-hover":"","button-background":"","button-background-hover":"","button-border-color":"","button-border-hover-color":""},{"name":"accordion grey","title":"#7d7d7d","title-hover":"","caption":"","content":"#7d7d7d","icon":"","link":"","link-hover":"","divider":"","border":"","element-background":"","element-content":"","button-text":"","button-text-hover":"","button-background":"","button-background-hover":"","button-border-color":"","button-border-hover-color":""},{"name":"2018 Winner","title":"#ffffff","title-hover":"","caption":"#c9c9c9","content":"#c9c9c9","icon":"","link":"","link-hover":"","divider":"","border":"","element-background":"","element-content":"","button-text":"","button-text-hover":"","button-background":"","button-background-hover":"","button-border-color":"","button-border-hover-color":""},{"name":"1000 client","title":"#ffffff","title-hover":"","caption":"#ece4d6","content":"#ece4d6","icon":"","link":"","link-hover":"","divider":"","border":"","element-background":"","element-content":"","button-text":"","button-text-hover":"","button-background":"","button-background-hover":"","button-border-color":"","button-border-hover-color":""},{"name":"95 Successful","title":"#ffffff","title-hover":"","caption":"#b1976b","content":"#b1976b","icon":"","link":"","link-hover":"","divider":"","border":"","element-background":"","element-content":"","button-text":"","button-text-hover":"","button-background":"","button-background-hover":"","button-border-color":"","button-border-hover-color":""},{"name":"COPORATE","title":"#ffffff","title-hover":"","caption":"#d9d1c4","content":"#d9d1c4","icon":"","link":"","link-hover":"","divider":"#d9d1c4","border":"","element-background":"","element-content":"","button-text":"","button-text-hover":"","button-background":"","button-background-hover":"","button-border-color":"","button-border-hover-color":""},{"name":"2018 white","title":"#ffffff","title-hover":"","caption":"#c9c9c9","content":"#c9c9c9","icon":"","link":"","link-hover":"","divider":"","border":"","element-background":"","element-content":"","button-text":"","button-text-hover":"","button-background":"","button-background-hover":"","button-border-color":"","button-border-hover-color":""},{"name":"Newsletter","title":"","title-hover":"","caption":"","content":"","icon":"","link":"","link-hover":"","divider":"","border":"#373737","element-background":"#373737","element-content":"#989898","button-text":"","button-text-hover":"","button-background":"","button-background-hover":"","button-border-color":"","button-border-hover-color":""},{"name":"Newsletter White","title":"","title-hover":"","caption":"","content":"","icon":"","link":"","link-hover":"","divider":"","border":"#ffffff","element-background":"#ffffff","element-content":"#969696","button-text":"","button-text-hover":"","button-background":"","button-background-hover":"","button-border-color":"","button-border-hover-color":""},{"name":"Grey Contact Form","title":"","title-hover":"","caption":"","content":"","icon":"","link":"","link-hover":"","divider":"","border":"","element-background":"#f5f5f5","element-content":"#636363","button-text":"","button-text-hover":"","button-background":"","button-background-hover":"","button-border-color":"","button-border-hover-color":""},{"name":"Grey Carousel","title":"","title-hover":"","caption":"","content":"","icon":"","link":"","link-hover":"","divider":"","border":"","element-background":"#efefef","element-content":"#b1976b","button-text":"","button-text-hover":"","button-background":"#efefef","button-background-hover":"","button-border-color":"","button-border-hover-color":""},{"name":"Testimonial Dark","title":"","title-hover":"","caption":"","content":"","icon":"","link":"","link-hover":"","divider":"","border":"#b1a17d","element-background":"#b1a17d","element-content":"","button-text":"","button-text-hover":"","button-background":"","button-background-hover":"","button-border-color":"","button-border-hover-color":""},{"name":"Brown Title Link","title":"#9f8862","title-hover":"#3d3d3d","caption":"","content":"","icon":"","link":"","link-hover":"","divider":"","border":"","element-background":"","element-content":"","button-text":"","button-text-hover":"","button-background":"","button-background-hover":"","button-border-color":"","button-border-hover-color":""}],"blog-grid-divider-color":"#ffd115","tag-cloud-text-color":"#ffffff","tag-cloud-background-color":"#b1976b","tag-cloud-border-color":"#b1976b","page-title-background-gradient-max-opacity":"1","page-title-background-gradient-color":"#000","single-blog-title-background-gradient-max-opacity":"1","single-blog-title-background-gradient-color":"#000","fixed-navigation-background-color":"","logo-bottom-border-color":"#b39a96","load-more-button-text":"#968481","load-more-button-border":"#968481","top-cart-title-color":"#000000","top-cart-info-color":"#6c6c6c","top-cart-view-cart-background-color":"#f4f4f4","top-cart-checkout-background-color":"#000000","custom-menu-widget-box-style-text":"#474747","custom-menu-widget-box-style-background":"#b1976b","custom-menu-widget-box-style-text-active":"#ffffff","top-bar-right-button-background":"#b1976b"},"attorna_plugin":{"enable-srcset":"disable","thumbnail-sizing":[{"name":"Personnel Thumbnail","width":"700","height":"500","hard-crop":""},{"name":"Portfolio Thumbnail","width":"700","height":"450","hard-crop":""},{"name":"Portfolio Thumbnail Portrait","width":"700","height":"660","hard-crop":""},{"name":"Portfolio Thumbnail Portrait 2","width":"600","height":"800","hard-crop":""},{"name":"Large Landscape","width":"1280","height":"580","hard-crop":""},{"name":"Large Landscape 2","width":"1550","height":"700","hard-crop":""},{"name":"Portfolio Side Description Large","width":"900","height":"500","hard-crop":""},{"name":"Blog Full Thumbnail","width":"1100","height":"490","hard-crop":""},{"name":"Personnel Square","width":"600","height":"600","hard-crop":""},{"name":"Large Landscape 3","width":"1500","height":"1000","hard-crop":""},{"name":"Gallery Portrait","width":"500","height":"600","hard-crop":""},{"name":"Port Large","width":"1500","height":"590","hard-crop":""}],"consent-item":"","disable-cookie-youtube":"disable","privacy-cookie-time":"30","privacy-notification-position":"bottom-bar","privacy-box-button-color":"#1a49a8","privacy-form-logo":"","privacy-form-input-button-color":"#1a49a8","privacy-form-save-button-color":"#1a49a8","lightbox":"lightGallery","ilightbox-skin":"dark","link-to-lightbox":"enable","lightbox-video-autoplay":"enable","additional-css":"","additional-mobile-css":"","additional-head-script":"","additional-head-script2":"","additional-script":"","enable-maintenance":"disable","maintenance-page":"2","enable-preload":"disable","preload-image":""}}